MANIFEST.in
README.txt
VERSION.txt
requirements.txt
setup.py
bbcu.vennDiagram.egg-info/PKG-INFO
bbcu.vennDiagram.egg-info/SOURCES.txt
bbcu.vennDiagram.egg-info/dependency_links.txt
bbcu.vennDiagram.egg-info/requires.txt
bbcu.vennDiagram.egg-info/top_level.txt
scripts/create-venn.py
vennDiagram/__init__.py
vennDiagram/d3.v4.js
vennDiagram/intersections.jsonp
vennDiagram/venn-diagram.html
vennDiagram/venn.v1.js
vennDiagram/wis_logo_heb_v1.png
vennDiagram/venn-diagram-example/input/a.csv
vennDiagram/venn-diagram-example/input/b.csv
vennDiagram/venn-diagram-example/input/c.csv
vennDiagram/venn-diagram-example/output/log.txt
vennDiagram/venn-diagram-example/output/filtered_genes/a_filtered.csv
vennDiagram/venn-diagram-example/output/filtered_genes/b_filtered.csv
vennDiagram/venn-diagram-example/output/filtered_genes/c_filtered.csv
vennDiagram/venn-diagram-example/output/intersections/a_b_c_intersected.csv
vennDiagram/venn-diagram-example/output/intersections/a_b_intersected.csv
vennDiagram/venn-diagram-example/output/intersections/a_c_intersected.csv
vennDiagram/venn-diagram-example/output/intersections/b_c_intersected.csv
vennDiagram/venn-diagram-example/output/intersections/summary_intersections.csv
vennDiagram/venn-diagram-example/output/venn-diagram/d3.v4.js
vennDiagram/venn-diagram-example/output/venn-diagram/intersections.jsonp
vennDiagram/venn-diagram-example/output/venn-diagram/venn-diagram.html
vennDiagram/venn-diagram-example/output/venn-diagram/venn.v1.js
vennDiagram/venn-diagram-example/output/venn-diagram/wis_logo_heb_v1.png