Metadata-Version: 1.0
Name: bbcu.vennDiagram
Version: 1.0.21
Summary: Create venn diagram from intersection between input files.
Home-page: UNKNOWN
Author: Refael Kohen
Author-email: refael.kohen@weizmann.ac.il
License: UNKNOWN
Platform: UNKNOWN
